{
  "$schema": "https://raw.githubusercontent.com/spdx/spdx-spec/v2.2.1/schemas/spdx-schema.json",
  "spdxVersion": "SPDX-2.2",
  "dataLicense": "CC0-1.0",
  "SPDXID": "SPDXRef-DOCUMENT",
  "documentNamespace": "https://spdx.org/spdxdocs/bzip2-x64-windows-1.0.8#3-f705dfa4-60f8-4c9e-a288-4e283dd5bc33",
  "name": "bzip2:x64-windows@1.0.8#3 29cfbc197d4db4bb665618ce7fc151833568137d7835176633c5dd5012bbeeef",
  "creationInfo": {
    "creators": [
      "Tool: vcpkg-5fdee72bc1fceca198fb1ab7589837206a8b81ba"
    ],
    "created": "2022-11-21T10:26:35Z"
  },
  "relationships": [
    {
      "spdxElementId": "SPDXRef-port",
      "relationshipType": "GENERATES",
      "relatedSpdxElement": "SPDXRef-binary"
    },
    {
      "spdxElementId": "SPDXRef-port",
      "relationshipType": "CONTAINS",
      "relatedSpdxElement": "SPDXRef-file-0"
    },
    {
      "spdxElementId": "SPDXRef-port",
      "relationshipType": "CONTAINS",
      "relatedSpdxElement": "SPDXRef-file-1"
    },
    {
      "spdxElementId": "SPDXRef-port",
      "relationshipType": "CONTAINS",
      "relatedSpdxElement": "SPDXRef-file-2"
    },
    {
      "spdxElementId": "SPDXRef-port",
      "relationshipType": "CONTAINS",
      "relatedSpdxElement": "SPDXRef-file-3"
    },
    {
      "spdxElementId": "SPDXRef-port",
      "relationshipType": "CONTAINS",
      "relatedSpdxElement": "SPDXRef-file-4"
    },
    {
      "spdxElementId": "SPDXRef-port",
      "relationshipType": "CONTAINS",
      "relatedSpdxElement": "SPDXRef-file-5"
    },
    {
      "spdxElementId": "SPDXRef-binary",
      "relationshipType": "GENERATED_FROM",
      "relatedSpdxElement": "SPDXRef-port"
    },
    {
      "spdxElementId": "SPDXRef-file-0",
      "relationshipType": "CONTAINED_BY",
      "relatedSpdxElement": "SPDXRef-port"
    },
    {
      "spdxElementId": "SPDXRef-file-1",
      "relationshipType": "CONTAINED_BY",
      "relatedSpdxElement": "SPDXRef-port"
    },
    {
      "spdxElementId": "SPDXRef-file-2",
      "relationshipType": "CONTAINED_BY",
      "relatedSpdxElement": "SPDXRef-port"
    },
    {
      "spdxElementId": "SPDXRef-file-3",
      "relationshipType": "CONTAINED_BY",
      "relatedSpdxElement": "SPDXRef-port"
    },
    {
      "spdxElementId": "SPDXRef-file-4",
      "relationshipType": "CONTAINED_BY",
      "relatedSpdxElement": "SPDXRef-port"
    },
    {
      "spdxElementId": "SPDXRef-file-5",
      "relationshipType": "CONTAINED_BY",
      "relatedSpdxElement": "SPDXRef-port"
    },
    {
      "spdxElementId": "SPDXRef-file-5",
      "relationshipType": "DEPENDENCY_MANIFEST_OF",
      "relatedSpdxElement": "SPDXRef-port"
    }
  ],
  "packages": [
    {
      "name": "bzip2",
      "SPDXID": "SPDXRef-port",
      "versionInfo": "1.0.8#3",
      "downloadLocation": "git+https://github.com/Microsoft/vcpkg#ports/bzip2",
      "homepage": "https://sourceware.org/bzip2/",
      "licenseConcluded": "bzip2-1.0.6",
      "licenseDeclared": "NOASSERTION",
      "copyrightText": "NOASSERTION",
      "description": "bzip2 is a freely available, patent free, high-quality data compressor. It typically compresses files to within 10% to 15% of the best available techniques (the PPM family of statistical compressors), whilst being around twice as fast at compression and six times faster at decompression.",
      "comment": "This is the port (recipe) consumed by vcpkg."
    },
    {
      "name": "bzip2:x64-windows",
      "SPDXID": "SPDXRef-binary",
      "versionInfo": "29cfbc197d4db4bb665618ce7fc151833568137d7835176633c5dd5012bbeeef",
      "downloadLocation": "NONE",
      "licenseConcluded": "bzip2-1.0.6",
      "licenseDeclared": "NOASSERTION",
      "copyrightText": "NOASSERTION",
      "comment": "This is a binary package built by vcpkg."
    },
    {
      "SPDXID": "SPDXRef-resource-1",
      "name": "bzip2-${BZIP2_VERSION}.tar.gz",
      "packageFileName": "bzip2-${BZIP2_VERSION}.tar.gz",
      "downloadLocation": "https://sourceware.org/pub/bzip2/bzip2-${BZIP2_VERSION}.tar.gz",
      "licenseConcluded": "NOASSERTION",
      "licenseDeclared": "NOASSERTION",
      "copyrightText": "NOASSERTION",
      "checksums": [
        {
          "algorithm": "SHA512",
          "checksumValue": "083f5e675d73f3233c7930ebe20425a533feedeaaa9d8cc86831312a6581cefbe6ed0d08d2fa89be81082f2a5abdabca8b3c080bf97218a1bd59dc118a30b9f3"
        }
      ]
    }
  ],
  "files": [
    {
      "fileName": "./bzip2.pc.in",
      "SPDXID": "SPDXRef-file-0",
      "checksums": [
        {
          "algorithm": "SHA256",
          "checksumValue": "ec5bae2705896aa6f2ac5eb2b02c5512568203808c8427484b5eef1da670df91"
        }
      ],
      "licenseConcluded": "NOASSERTION",
      "copyrightText": "NOASSERTION"
    },
    {
      "fileName": "./CMakeLists.txt",
      "SPDXID": "SPDXRef-file-1",
      "checksums": [
        {
          "algorithm": "SHA256",
          "checksumValue": "4f14b283a0be8ae8ad8a6c6db288ff5ffe3af6d82506fac266532b11ea9a8a33"
        }
      ],
      "licenseConcluded": "NOASSERTION",
      "copyrightText": "NOASSERTION"
    },
    {
      "fileName": "./fix-import-export-macros.patch",
      "SPDXID": "SPDXRef-file-2",
      "checksums": [
        {
          "algorithm": "SHA256",
          "checksumValue": "38918c1257c884cc5cde39d9f4235d0e71574f20c7e5ec686a506612f647495e"
        }
      ],
      "licenseConcluded": "NOASSERTION",
      "copyrightText": "NOASSERTION"
    },
    {
      "fileName": "./portfile.cmake",
      "SPDXID": "SPDXRef-file-3",
      "checksums": [
        {
          "algorithm": "SHA256",
          "checksumValue": "ffef2f051e412a3fd1ef78cd18439c113f8ae4d0d49e581f19697704331661de"
        }
      ],
      "licenseConcluded": "NOASSERTION",
      "copyrightText": "NOASSERTION"
    },
    {
      "fileName": "./usage",
      "SPDXID": "SPDXRef-file-4",
      "checksums": [
        {
          "algorithm": "SHA256",
          "checksumValue": "75d339011fc11a43ee5093142ca1e8cb5e54db2ac93822abc5de694cda5a9881"
        }
      ],
      "licenseConcluded": "NOASSERTION",
      "copyrightText": "NOASSERTION"
    },
    {
      "fileName": "./vcpkg.json",
      "SPDXID": "SPDXRef-file-5",
      "checksums": [
        {
          "algorithm": "SHA256",
          "checksumValue": "1e3d45a5e6f560a0c49bfba02296c497b7f8d2d0c86006eca511357efe7b86c8"
        }
      ],
      "licenseConcluded": "NOASSERTION",
      "copyrightText": "NOASSERTION"
    }
  ]
}
